README.rst
pyproject.toml
setup.py
src/durable_call/__init__.py
src/durable_call/call_store.py
src/durable_call/call_store.sql
src/durable_call/durable.py
src/durable_call/robust.py
src/durable_call/utils.py
src/durable_call.egg-info/PKG-INFO
src/durable_call.egg-info/SOURCES.txt
src/durable_call.egg-info/dependency_links.txt
src/durable_call.egg-info/requires.txt
src/durable_call.egg-info/top_level.txt