Metadata-Version: 2.1
Name: durable-call
Version: 0.1.0
Summary: Durable Local and Remote Function Calls
Author-email: Parantapa Bhattacharya <pb+pypi@parantapa.net>
Project-URL: Homepage, http://github.com/parantapa/durable-call
Classifier: Programming Language :: Python :: 3
Classifier: License :: OSI Approved :: MIT License
Classifier: Operating System :: OS Independent
Requires-Python: >=3.10
